infocenter/__init__.py
infocenter/mail.py
infocenter/sms.py
infocenter/weather.py
tests/__init__.py
jason_lee_tools-0.10.0.dist-info/LICENSE
jason_lee_tools-0.10.0.dist-info/METADATA
jason_lee_tools-0.10.0.dist-info/WHEEL
jason_lee_tools-0.10.0.dist-info/top_level.txt
jason_lee_tools-0.10.0.dist-info/RECORD
