Metadata-Version: 2.1
Name: jason-lee-tools
Version: 0.10.0
Summary: sdk for ali(Jason Lee)'s environment
Home-page: https://github.com/neulf/ali-tools
Author: Jason Lee
Author-email: master@lifang.fun
Classifier: Programming Language :: Python :: 3
Classifier: License :: OSI Approved :: MIT License
Classifier: Operating System :: OS Independent
Requires-Python: >=3.6
License-File: LICENSE
Requires-Dist: requests
